.hgignore
.hgtags
CHANGES.rst
README.rst
buildout.cfg
setup.py
src/gocept/__init__.py
src/gocept.recipe.bowerstaticbundler.egg-info/PKG-INFO
src/gocept.recipe.bowerstaticbundler.egg-info/SOURCES.txt
src/gocept.recipe.bowerstaticbundler.egg-info/dependency_links.txt
src/gocept.recipe.bowerstaticbundler.egg-info/entry_points.txt
src/gocept.recipe.bowerstaticbundler.egg-info/namespace_packages.txt
src/gocept.recipe.bowerstaticbundler.egg-info/not-zip-safe
src/gocept.recipe.bowerstaticbundler.egg-info/requires.txt
src/gocept.recipe.bowerstaticbundler.egg-info/top_level.txt
src/gocept/recipe/__init__.py
src/gocept/recipe/bowerstaticbundler/__init__.py
src/gocept/recipe/bowerstaticbundler/tests.py