Metadata-Version: 1.1
Name: gocept.recipe.bowerstaticbundler
Version: 1.2.2
Summary: Minifies and bundles JS and CSS files included with bowerstatic.
Home-page: https://bitbucket.org/gocept/gocept.recipe.bowerstaticbundler
Author: gocept gmbh & co. kg
Author-email: mail@gocept.org
License: GPL
Keywords: bower bowerstatic minify bundle css js javascript buildout recipe
Platform: UNKNOWN
Classifier: Development Status :: 3 - Alpha
Classifier: Environment :: Console
Classifier: Framework :: Buildout
Classifier: Framework :: Buildout :: Recipe
Classifier: Intended Audience :: Developers
Classifier: License :: OSI Approved
Classifier: License :: OSI Approved :: Zope Public License
Classifier: Natural Language :: English
Classifier: Operating System :: OS Independent
Classifier: Programming Language :: Python
Classifier: Programming Language :: Python :: 2 :: Only
Classifier: Programming Language :: Python :: 2.7
Classifier: Programming Language :: Python :: Implementation :: CPython
Classifier: Topic :: Software Development :: Build Tools
